eth_pydantic_types/__init__.py
eth_pydantic_types/_error.py
eth_pydantic_types/_main.py
eth_pydantic_types/abi.py
eth_pydantic_types/address.py
eth_pydantic_types/bip122.py
eth_pydantic_types/py.typed
eth_pydantic_types/serializers.py
eth_pydantic_types/utils.py
eth_pydantic_types/version.py
eth_pydantic_types/hex/__init__.py
eth_pydantic_types/hex/base.py
eth_pydantic_types/hex/bytes.py
eth_pydantic_types/hex/int.py
eth_pydantic_types/hex/str.py
eth_pydantic_types-0.2.2.dist-info/licenses/LICENSE
eth_pydantic_types-0.2.2.dist-info/METADATA
eth_pydantic_types-0.2.2.dist-info/WHEEL
eth_pydantic_types-0.2.2.dist-info/top_level.txt
eth_pydantic_types-0.2.2.dist-info/RECORD
